variationist/__init__.py
variationist/inspector.py
variationist/utils.py
variationist/visualizer.py
variationist/data/__init__.py
variationist/data/preprocess_utils.py
variationist/data/tokenization.py
variationist/data/tokenization_utils.py
variationist/metrics/__init__.py
variationist/metrics/corpus_statistics.py
variationist/metrics/lexical_artifacts.py
variationist/metrics/lexical_variation.py
variationist/metrics/metrics.py
variationist/metrics/pmi.py
variationist/metrics/shared_metrics.py
variationist/metrics/utils.py
variationist/visualization/__init__.py
variationist/visualization/altair_chart.py
variationist/visualization/bar_chart.py
variationist/visualization/binned_geo_chart.py
variationist/visualization/chart.py
variationist/visualization/chart_utils.py
variationist/visualization/choropleth_chart.py
variationist/visualization/density_geo_chart.py
variationist/visualization/diversity_bar_chart.py
variationist/visualization/heatmap_chart.py
variationist/visualization/line_chart.py
variationist/visualization/plotly_chart.py
variationist/visualization/scatter_chart.py
variationist/visualization/scatter_geo_chart.py
variationist/visualization/stats_bar_chart.py
variationist/visualization/temporal_line_chart.py
variationist/visualization/text_only_bar_chart.py
variationist-0.1.6.dist-info/METADATA
variationist-0.1.6.dist-info/WHEEL
variationist-0.1.6.dist-info/licenses/LICENSE
variationist-0.1.6.dist-info/RECORD
