Metadata-Version: 2.4
Name: variationist
Version: 0.1.6
Summary: Variationist: Exploring multifaceted variation and bias in written language data
Project-URL: Homepage, https://github.com/dhfbk/variationist
Project-URL: Documentation, https://variationist.readthedocs.io/en/latest
Project-URL: Issues, https://github.com/dhfbk/variationist/issues
Author: Alan Ramponi, Camilla Casula, Stefano Menini
License: MIT License
License-File: LICENSE
Keywords: NLP,bias in NLP,computational linguistics,corpus analysis,language variation
Classifier: License :: OSI Approved :: MIT License
Classifier: Operating System :: OS Independent
Classifier: Programming Language :: Python :: 3
Requires-Python: >=3.10
Requires-Dist: altair==5.2.0
Requires-Dist: datasets>=3.2.0
Requires-Dist: emoji==2.10.1
Requires-Dist: geopandas==1.0.1
Requires-Dist: jedi>=0.16
Requires-Dist: kaleido==0.2.1
Requires-Dist: numpy<2.2.0,>=1.26.0
Requires-Dist: pandas<2.3.0,>=2.2.2
Requires-Dist: plotly==5.19.0
Requires-Dist: pyogrio>=0.7.2
Requires-Dist: setuptools<=80.6.0
Requires-Dist: stopwordsiso==0.6.1
Requires-Dist: transformers>=4.47.0
Requires-Dist: vl-convert-python==1.2.4
